diffcord/__init__.py
diffcord/api.py
diffcord/client.py
diffcord/error.py
diffcord/vote.py
diffcord-1.0.3.dist-info/LICENSE
diffcord-1.0.3.dist-info/METADATA
diffcord-1.0.3.dist-info/WHEEL
diffcord-1.0.3.dist-info/top_level.txt
diffcord-1.0.3.dist-info/RECORD
