Metadata-Version: 2.1
Name: diffcord
Version: 1.0.3
Summary: A Python wrapper for the Diffcord API written in Python.
Author: jadelasmar4@gmail.com
Project-URL: Github, https://github.com/diff-cord/python-sdk
Keywords: diffcord,diffcord-api,diffcord-api-wrapper,diffcord-api-python-wrapper,diffcord-api-python
Requires-Python: >=3.7.0
License-File: LICENSE
Requires-Dist: httpx (==0.23.3)
Requires-Dist: tornado (==6.2)
